network_manager_dispatcher_app/__init__.py
network_manager_dispatcher_app/app_logger.py
network_manager_dispatcher_app/device_state.py
network_manager_dispatcher_app/dnsleaktest.py
network_manager_dispatcher_app/nm_dispatcher_app.py
network_manager_dispatcher_app/sound_thread.py
network_manager_dispatcher_app/sox_player.py
network_manager_dispatcher_app-0.0.10.dist-info/LICENSE
network_manager_dispatcher_app-0.0.10.dist-info/METADATA
network_manager_dispatcher_app-0.0.10.dist-info/WHEEL
network_manager_dispatcher_app-0.0.10.dist-info/top_level.txt
network_manager_dispatcher_app-0.0.10.dist-info/RECORD
