Metadata-Version: 2.1
Name: network-manager-dispatcher-app
Version: 0.0.10
Summary: A Job for Network Manager
Home-page: https://github.com/meads/network-manager-dispatcher-app/
Author: Hat
Author-email: resetheadhat@gmail.com
License: UNKNOWN
Project-URL: Bug Tracker, https://github.com/meads/network-manager-dispatcher-app/issues
Platform: UNKNOWN
Classifier: Programming Language :: Python :: 3
Classifier: License :: OSI Approved :: MIT License
Classifier: Operating System :: POSIX :: Linux
Requires-Python: >=3.6
License-File: LICENSE
